ilderness/__init__.py
ilderness/solo/__init__.py
ilderness/solo/model/__init__.py
ilderness/solo/model/account_pb2.py
ilderness/solo/model/account_pb2.pyi
ilderness/solo/model/account_pb2_grpc.py
ilderness/solo/model/credential_pb2.py
ilderness/solo/model/credential_pb2.pyi
ilderness/solo/model/credential_pb2_grpc.py
ilderness/solo/model/user_pb2.py
ilderness/solo/model/user_pb2.pyi
ilderness/solo/model/user_pb2_grpc.py
ilderness/solo/service/__init__.py
ilderness/solo/service/account_service_pb2.py
ilderness/solo/service/account_service_pb2.pyi
ilderness/solo/service/account_service_pb2_grpc.py
ilderness_solo_proto-0.0.5.dist-info/LICENSE
ilderness_solo_proto-0.0.5.dist-info/METADATA
ilderness_solo_proto-0.0.5.dist-info/WHEEL
ilderness_solo_proto-0.0.5.dist-info/top_level.txt
ilderness_solo_proto-0.0.5.dist-info/RECORD
